{
    "settings": {
        "autoUpdate": true,
        "autoUpdateNotification": true,
        "useQuickCss": true,
        "themeLinks": [
            "https://raw.githubusercontent.com/DiscordStyles/RadialStatus/deploy/RadialStatus.theme.css",
            "https://raw.githubusercontent.com/mwittrien/BetterDiscordAddons/refs/heads/master/Themes/SettingsModal/SettingsModal.theme.css",
            "https://refact0r.github.io/midnight-discord/build/midnight.css"
        ],
        "enabledThemes": [],
        "enableReactDevtools": false,
        "frameless": false,
        "transparent": false,
        "winCtrlQ": false,
        "disableMinSize": false,
        "winNativeTitleBar": false,
        "plugins": {
            "ChatInputButtonAPI": {
                "enabled": true
            },
            "CommandsAPI": {
                "enabled": true
            },
            "DynamicImageModalAPI": {
                "enabled": true
            },
            "MemberListDecoratorsAPI": {
                "enabled": true
            },
            "MessageAccessoriesAPI": {
                "enabled": true
            },
            "MessageDecorationsAPI": {
                "enabled": true
            },
            "MessageEventsAPI": {
                "enabled": true
            },
            "MessagePopoverAPI": {
                "enabled": true
            },
            "MessageUpdaterAPI": {
                "enabled": true
            },
            "ServerListAPI": {
                "enabled": false
            },
            "UserSettingsAPI": {
                "enabled": true
            },
            "AccountPanelServerProfile": {
                "enabled": true,
                "prioritizeServerProfile": false
            },
            "AlwaysAnimate": {
                "enabled": true
            },
            "AlwaysExpandRoles": {
                "enabled": true
            },
            "AlwaysTrust": {
                "enabled": false
            },
            "AnonymiseFileNames": {
                "enabled": true,
                "anonymiseByDefault": true,
                "method": 0,
                "randomisedLength": 7,
                "consistent": "image"
            },
            "AppleMusicRichPresence": {
                "enabled": false
            },
            "BANger": {
                "enabled": false
            },
            "BetterFolders": {
                "enabled": true,
                "sidebar": true,
                "sidebarAnim": true,
                "closeAllFolders": false,
                "closeAllHomeButton": false,
                "closeOthers": false,
                "forceOpen": false,
                "keepIcons": false,
                "showFolderIcon": 1
            },
            "BetterGifAltText": {
                "enabled": false
            },
            "BetterGifPicker": {
                "enabled": false
            },
            "BetterNotesBox": {
                "enabled": false
            },
            "BetterRoleContext": {
                "enabled": true
            },
            "BetterRoleDot": {
                "enabled": false
            },
            "BetterSessions": {
                "enabled": true,
                "backgroundCheck": false,
                "checkInterval": 20
            },
            "BetterSettings": {
                "enabled": true,
                "disableFade": true,
                "organizeMenu": true,
                "eagerLoad": true
            },
            "BetterUploadButton": {
                "enabled": true
            },
            "BiggerStreamPreview": {
                "enabled": true
            },
            "BlurNSFW": {
                "enabled": false
            },
            "CallTimer": {
                "enabled": true,
                "format": "stopwatch"
            },
            "ClearURLs": {
                "enabled": false
            },
            "ClientTheme": {
                "enabled": true,
                "color": "13171b"
            },
            "ColorSighted": {
                "enabled": false
            },
            "ConsoleJanitor": {
                "enabled": false,
                "disableLoggers": false,
                "disableSpotifyLogger": true,
                "whitelistedLoggers": "GatewaySocket; Routing/Utils"
            },
            "ConsoleShortcuts": {
                "enabled": false
            },
            "CopyEmojiMarkdown": {
                "enabled": true
            },
            "CopyFileContents": {
                "enabled": true
            },
            "CopyUserURLs": {
                "enabled": true
            },
            "CrashHandler": {
                "enabled": true,
                "attemptToPreventCrashes": true,
                "attemptToNavigateToHome": false
            },
            "CtrlEnterSend": {
                "enabled": false
            },
            "CustomIdle": {
                "enabled": false
            },
            "CustomRPC": {
                "enabled": false,
                "type": 0,
                "timestampMode": 3,
                "appID": "1264678329446039583",
                "appName": "Dark and Darker",
                "imageBig": "https://github.com/pixo2000/Mod-Data/blob/main/Voidcube/favicon.png?raw=true",
                "startTime": 5
            },
            "Dearrow": {
                "enabled": false
            },
            "Decor": {
                "enabled": false
            },
            "DisableCallIdle": {
                "enabled": true
            },
            "DontRoundMyTimestamps": {
                "enabled": true
            },
            "Experiments": {
                "enabled": true,
                "toolbarDevMenu": false
            },
            "F8Break": {
                "enabled": false
            },
            "FakeNitro": {
                "enabled": false,
                "enableStickerBypass": true,
                "enableStreamQualityBypass": true,
                "enableEmojiBypass": true,
                "transformEmojis": true,
                "transformStickers": true,
                "transformCompoundSentence": false
            },
            "FakeProfileThemes": {
                "enabled": true,
                "nitroFirst": true
            },
            "FavoriteEmojiFirst": {
                "enabled": true
            },
            "FavoriteGifSearch": {
                "enabled": false,
                "searchOption": "hostandpath"
            },
            "FixCodeblockGap": {
                "enabled": true
            },
            "FixImagesQuality": {
                "enabled": true
            },
            "FixSpotifyEmbeds": {
                "enabled": true
            },
            "FixYoutubeEmbeds": {
                "enabled": true
            },
            "ForceOwnerCrown": {
                "enabled": true
            },
            "FriendInvites": {
                "enabled": true
            },
            "FriendsSince": {
                "enabled": true
            },
            "FullSearchContext": {
                "enabled": true
            },
            "GameActivityToggle": {
                "enabled": true,
                "oldIcon": false
            },
            "GifPaste": {
                "enabled": false
            },
            "GreetStickerPicker": {
                "enabled": false,
                "greetMode": "Greet"
            },
            "IgnoreActivities": {
                "enabled": false,
                "listMode": 0,
                "idsList": "",
                "ignorePlaying": false,
                "ignoreStreaming": false,
                "ignoreListening": false,
                "ignoreWatching": false,
                "ignoreCompeting": false
            },
            "iLoveSpam": {
                "enabled": false
            },
            "ImageLink": {
                "enabled": false
            },
            "ImageZoom": {
                "enabled": true,
                "size": 100,
                "zoom": 2,
                "saveZoomValues": true,
                "nearestNeighbour": false,
                "square": false,
                "invertScroll": true,
                "zoomSpeed": 0.5
            },
            "ImplicitRelationships": {
                "enabled": false,
                "sortByAffinity": true
            },
            "InvisibleChat": {
                "enabled": false,
                "savedPasswords": "password, Password"
            },
            "KeepCurrentChannel": {
                "enabled": true
            },
            "LastFMRichPresence": {
                "enabled": false,
                "shareUsername": false,
                "shareSong": true,
                "hideWithSpotify": true,
                "statusName": "some music",
                "nameFormat": "status-name",
                "useListeningStatus": false,
                "missingArt": "lastfmLogo",
                "showLastFmLogo": true
            },
            "LoadingQuotes": {
                "enabled": true,
                "replaceEvents": true,
                "enablePluginPresetQuotes": false,
                "enableDiscordPresetQuotes": false,
                "additionalQuotes": "pixo2000 on top!",
                "additionalQuotesDelimiter": "|"
            },
            "MemberCount": {
                "enabled": true,
                "memberList": true,
                "toolTip": true,
                "voiceActivity": true
            },
            "MentionAvatars": {
                "enabled": true,
                "showAtSymbol": true
            },
            "MessageClickActions": {
                "enabled": true,
                "enableDeleteOnClick": true,
                "enableDoubleClickToEdit": true,
                "enableDoubleClickToReply": true,
                "requireModifier": false
            },
            "MessageLatency": {
                "enabled": false
            },
            "MessageLinkEmbeds": {
                "enabled": true,
                "listMode": "blacklist",
                "idList": "",
                "automodEmbeds": "never"
            },
            "MessageLogger": {
                "enabled": true,
                "deleteStyle": "overlay",
                "logDeletes": true,
                "collapseDeleted": true,
                "logEdits": true,
                "inlineEdits": true,
                "ignoreBots": true,
                "ignoreSelf": false,
                "ignoreUsers": "",
                "ignoreChannels": "",
                "ignoreGuilds": ""
            },
            "MessageTags": {
                "enabled": true,
                "tagsList": {}
            },
            "MoreCommands": {
                "enabled": false
            },
            "MoreKaomoji": {
                "enabled": false
            },
            "MoreUserTags": {
                "enabled": false
            },
            "Moyai": {
                "enabled": false
            },
            "MutualGroupDMs": {
                "enabled": true
            },
            "NewGuildSettings": {
                "enabled": false,
                "guild": true,
                "messages": 3,
                "everyone": true,
                "role": true,
                "highlights": true,
                "events": true,
                "showAllChannels": true
            },
            "NoBlockedMessages": {
                "enabled": false
            },
            "NoDevtoolsWarning": {
                "enabled": false
            },
            "NoF1": {
                "enabled": false
            },
            "NoMaskedUrlPaste": {
                "enabled": false
            },
            "NoMosaic": {
                "enabled": false
            },
            "NoOnboardingDelay": {
                "enabled": true
            },
            "NoPendingCount": {
                "enabled": false
            },
            "NoProfileThemes": {
                "enabled": false
            },
            "NoReplyMention": {
                "enabled": false
            },
            "NormalizeMessageLinks": {
                "enabled": false
            },
            "NoRPC": {
                "enabled": false
            },
            "NoScreensharePreview": {
                "enabled": true
            },
            "NoServerEmojis": {
                "enabled": false
            },
            "NoSystemBadge": {
                "enabled": false
            },
            "NotificationVolume": {
                "enabled": false
            },
            "NoTypingAnimation": {
                "enabled": false
            },
            "NoUnblockToJump": {
                "enabled": false
            },
            "NSFWGateBypass": {
                "enabled": false
            },
            "oneko": {
                "enabled": false
            },
            "OnePingPerDM": {
                "enabled": false
            },
            "OpenInApp": {
                "enabled": false
            },
            "OverrideForumDefaults": {
                "enabled": false
            },
            "PartyMode": {
                "enabled": false
            },
            "PauseInvitesForever": {
                "enabled": true
            },
            "PermissionFreeWill": {
                "enabled": false,
                "lockout": true,
                "onboarding": true
            },
            "PermissionsViewer": {
                "enabled": true,
                "permissionsSortOrder": 0
            },
            "petpet": {
                "enabled": true
            },
            "PictureInPicture": {
                "enabled": false
            },
            "PinDMs": {
                "enabled": true,
                "pinOrder": 0,
                "dmSectionCollapsed": false,
                "canCollapseDmSection": false,
                "userBasedCategoryList": {
                    "816347872181878786": [
                        {
                            "id": "xzzpi65rs4m",
                            "name": "Pin",
                            "color": 10070709,
                            "collapsed": false,
                            "channels": [
                                "1093501704894423232",
                                "866296667589967892"
                            ]
                        }
                    ],
                    "858397118242226177": []
                }
            },
            "PlainFolderIcon": {
                "enabled": true
            },
            "PlatformIndicators": {
                "enabled": true,
                "list": true,
                "badges": true,
                "messages": true,
                "colorMobileIndicator": true
            },
            "PreviewMessage": {
                "enabled": true
            },
            "QuickMention": {
                "enabled": false
            },
            "QuickReply": {
                "enabled": false
            },
            "ReactErrorDecoder": {
                "enabled": false
            },
            "ReadAllNotificationsButton": {
                "enabled": false
            },
            "RelationshipNotifier": {
                "enabled": true,
                "notices": true,
                "offlineRemovals": true,
                "friends": true,
                "friendRequestCancels": true,
                "servers": true,
                "groups": true
            },
            "ReplaceGoogleSearch": {
                "enabled": false
            },
            "ReplyTimestamp": {
                "enabled": false
            },
            "RevealAllSpoilers": {
                "enabled": false
            },
            "ReverseImageSearch": {
                "enabled": false
            },
            "ReviewDB": {
                "enabled": true,
                "notifyReviews": true,
                "showWarning": true,
                "hideTimestamps": false,
                "hideBlockedUsers": true
            },
            "RoleColorEverywhere": {
                "enabled": false
            },
            "SecretRingToneEnabler": {
                "enabled": false
            },
            "Summaries": {
                "enabled": true,
                "summaryExpiryThresholdDays": 3
            },
            "SendTimestamps": {
                "enabled": true,
                "replaceMessageContents": true
            },
            "ServerInfo": {
                "enabled": true
            },
            "ServerListIndicators": {
                "enabled": false
            },
            "ShikiCodeblocks": {
                "enabled": true,
                "theme": "https://raw.githubusercontent.com/shikijs/textmate-grammars-themes/2d87559c7601a928b9f7e0f0dda243d2fb6d4499/packages/tm-themes/themes/dark-plus.json",
                "tryHljs": "SECONDARY",
                "useDevIcon": "GREYSCALE",
                "bgOpacity": 100
            },
            "ShowAllMessageButtons": {
                "enabled": false
            },
            "ShowConnections": {
                "enabled": true,
                "iconSize": 32,
                "iconSpacing": 1
            },
            "ShowHiddenChannels": {
                "enabled": true,
                "hideUnreads": true,
                "showMode": 1,
                "defaultAllowedUsersAndRolesDropdownState": true
            },
            "ShowHiddenThings": {
                "enabled": true,
                "showTimeouts": true,
                "showInvitesPaused": true,
                "showModView": true,
                "disableDiscoveryFilters": true,
                "disableDisallowedDiscoveryFilters": true
            },
            "ShowMeYourName": {
                "enabled": false
            },
            "ShowTimeoutDuration": {
                "enabled": true,
                "displayStyle": "ssalggnikool"
            },
            "SilentMessageToggle": {
                "enabled": false
            },
            "SilentTyping": {
                "enabled": true,
                "showIcon": false,
                "contextMenu": true,
                "isEnabled": true
            },
            "SortFriendRequests": {
                "enabled": false
            },
            "SpotifyControls": {
                "enabled": false
            },
            "SpotifyCrack": {
                "enabled": false,
                "noSpotifyAutoPause": true,
                "keepSpotifyActivityOnIdle": false
            },
            "SpotifyShareCommands": {
                "enabled": false
            },
            "StartupTimings": {
                "enabled": false
            },
            "StickerPaste": {
                "enabled": false
            },
            "StreamerModeOnStream": {
                "enabled": false
            },
            "SuperReactionTweaks": {
                "enabled": false
            },
            "TextReplace": {
                "enabled": false
            },
            "ThemeAttributes": {
                "enabled": true
            },
            "Translate": {
                "enabled": true,
                "showChatBarButton": true,
                "service": "google",
                "deeplApiKey": "",
                "autoTranslate": false,
                "showAutoTranslateTooltip": true,
                "receivedInput": "auto",
                "receivedOutput": "de",
                "sentInput": "auto",
                "sentOutput": "en"
            },
            "TypingIndicator": {
                "enabled": true,
                "includeMutedChannels": false,
                "includeCurrentChannel": true,
                "indicatorMode": 3
            },
            "TypingTweaks": {
                "enabled": true,
                "alternativeFormatting": true,
                "showRoleColors": true,
                "showAvatars": true
            },
            "Unindent": {
                "enabled": false
            },
            "UnlockedAvatarZoom": {
                "enabled": false
            },
            "UnsuppressEmbeds": {
                "enabled": true
            },
            "UserMessagesPronouns": {
                "enabled": false
            },
            "UserVoiceShow": {
                "enabled": true,
                "showInUserProfileModal": true,
                "showInMemberList": true,
                "showInMessages": true
            },
            "USRBG": {
                "enabled": false,
                "nitroFirst": true,
                "voiceBackground": true
            },
            "ValidReply": {
                "enabled": true
            },
            "ValidUser": {
                "enabled": true
            },
            "VoiceChatDoubleClick": {
                "enabled": false
            },
            "VcNarrator": {
                "enabled": true,
                "voice": "Microsoft Hedda - German (Germany)",
                "volume": 1,
                "rate": 1,
                "sayOwnName": false,
                "latinOnly": false,
                "joinMessage": "{{USER}} joined",
                "leaveMessage": "{{USER}} left",
                "moveMessage": "{{USER}} moved to {{CHANNEL}}",
                "muteMessage": "{{USER}} Muted",
                "unmuteMessage": "{{USER}} unmuted",
                "deafenMessage": "{{USER}} deafened",
                "undeafenMessage": "{{USER}} undeafened"
            },
            "VencordToolbox": {
                "enabled": true
            },
            "ViewIcons": {
                "enabled": true,
                "format": "webp",
                "imgSize": "1024"
            },
            "ViewRaw": {
                "enabled": false,
                "clickMethod": "Left"
            },
            "VoiceDownload": {
                "enabled": true
            },
            "VoiceMessages": {
                "enabled": true
            },
            "VolumeBooster": {
                "enabled": true,
                "multiplier": 2
            },
            "WhoReacted": {
                "enabled": false
            },
            "XSOverlay": {
                "enabled": false
            },
            "YoutubeAdblock": {
                "enabled": true
            },
            "ExitSounds": {
                "enabled": true,
                "soundGuildId": "1201570186336157716",
                "soundId": "1253732865406013550"
            },
            "FollowUser": {
                "enabled": true,
                "executeOnFollow": true,
                "onlyManualTrigger": false,
                "followLeave": false,
                "autoMoveBack": false,
                "channelFull": true,
                "followUserId": ""
            },
            "InRole": {
                "enabled": true
            },
            "LoginWithQR": {
                "enabled": false
            },
            "NewPluginsManager": {
                "enabled": true
            },
            "NotifyUserChanges": {
                "enabled": true,
                "notifyStatus": true,
                "userIds": "",
                "notifyVoice": true,
                "persistNotifications": true
            },
            "SidebarChat": {
                "enabled": true
            },
            "VideoStartNotifier": {
                "enabled": true,
                "playInServer": true,
                "playInPrivate": true
            },
            "VoiceChatUtilities": {
                "enabled": true,
                "waitAfter": 5,
                "waitSeconds": 2
            },
            "WhosWatching": {
                "enabled": true,
                "showPanel": true
            },
            "NoTrack": {
                "enabled": true,
                "disableAnalytics": true
            },
            "Settings": {
                "enabled": true,
                "settingsLocation": "aboveNitro"
            },
            "SupportHelper": {
                "enabled": true,
                "dismissedDevBuildWarning": true
            },
            "MoreReact": {
                "enabled": true,
                "Max": 7
            },
            "RandomGary": {
                "enabled": true,
                "randomGarySendMethod": "link",
                "randomGaryImageSource": "catapi"
            },
            "FullUserInChatbox": {
                "enabled": true
            },
            "IrcColors": {
                "enabled": false
            },
            "BadgeAPI": {
                "enabled": true
            },
            "HideMedia": {
                "enabled": false
            },
            "ExpressionCloner": {
                "enabled": true
            },
            "CopyStickerLinks": {
                "enabled": false
            },
            "ImageFilename": {
                "enabled": false
            }
        },
        "notifications": {
            "timeout": 5000,
            "position": "bottom-right",
            "useNative": "not-focused",
            "logLimit": 50
        },
        "cloud": {
            "authenticated": true,
            "url": "https://api.vencord.dev/",
            "settingsSync": true,
            "settingsSyncVersion": 1757948462222
        },
        "eagerPatches": false
    },
    "quickCss": "@import url(\"https://gold-me.github.io/DiscordIcons/main.css\");\r\n@import url('https://ukriu.github.io/cssCord/Other/gradientDM.css');\r\n@import url('https://raw.githubusercontent.com/acheronx0577/Transparent-Quick-Switcher-Discord/main/Transparent%20Quick%20Switcher.css');\r\n/* @import url('https://raw.githubusercontent.com/Krammeth/css-snippets/refs/heads/main/PopoutsRevamped.css'); */\r\n@import url('https://raw.githubusercontent.com/ukriu/cssCord/refs/heads/main/Other/gradientML.css');\r\n/* @import url(\"https://raw.githubusercontent.com/Augenbl1ck/Discord-Styles/refs/heads/main/expProfile.css\"); */\r\n/* @import url('https://raw.githubusercontent.com/surgedevs/visual-refresh-compact-title-bar/refs/heads/main/desktop.css');   */\r\n:root {\r\n    --gDM-online: linear-gradient(to right, rgb(68, 105, 68) , transparent);\r\n    --gDM-offline: linear-gradient(to right, rgb(66, 66, 66) , transparent);\r\n    --gDM-dnd: linear-gradient(to right, rgb(130,70,70) , transparent);\r\n    --gDM-idle: linear-gradient(to right, rgb(135, 105, 75) , transparent);\r\n    --gDM-streaming: linear-gradient(to right, rgb(63, 33, 88) , transparent);\r\n    --gDM-border-radius: 12px;\r\n}\r\n[class*=\"member\"][class*=\"container\"] > [class^=childContainer] {\r\n    padding: 0;\r\n    & > [class^=memberInner] {\r\n        padding: 0 8px;\r\n        width: unset\r\n    }\r\n}\r\n\r\n\r\n/* Full sized gif picker */\r\n[class*='layerContainer_'] [class*='positionLayer__'] {\r\n    height: 100% !important;\r\n    [class*='drawerSizingWrapper__'] {\r\n        top: 3.5em !important;\r\n        height: calc(100% - 9em)\r\n    }\r\n}\r\n\r\n/* Hide elements where data-list-item-id contains \"nitro\" or \"shop\" */\r\na[data-list-item-id*=\"nitro\"],\r\na[data-list-item-id*=\"shop\"] {\r\n    display: none !important;\r\n}\r\n\r\n/* round messages on hovering, replies, and mentions */\r\n:root {\r\n  --round-messages-radius: 8px;\r\n}\r\n[class*=cozyMessage] {\r\n    margin-left: 4px;\r\n    border-radius: var(--round-messages-radius);\r\n}\r\n[class*=cozyMessage]:before {\r\n  width: 4px;\r\n  height: calc(100% - 1.5*var(--round-messages-radius));\r\n  align-self: center;\r\n  border-radius: 2px;\r\n  margin-left: calc(0.5*var(--round-messages-radius));\r\n}\r\n\r\n.visual-refresh section.panels_c48ade {\r\n  left: calc(var(--custom-guild-list-width) + var(--space-xs));\r\n  width: calc(100% - var(--custom-guild-list-width) - var(--space-xs)*2);\r\n  box-sizing: content-box;\r\n\r\n  .actionButtons_e131a9 button {\r\n    padding: 0;\r\n  }\r\n\r\n  /* GameActivityToggle Fix (delete if you don't use) */\r\n   .container__37e49 {\r\n    padding: var(--space-xxs);\r\n    gap: var(--space-4);\r\n    >.buttons__37e49 {\r\n      gap: 0;\r\n    }\r\n    >.avatarWrapper__37e49 {\r\n      min-width: 32px !important;\r\n      >.avatar__37e49 {\r\n        scale: 0.9;\r\n      }\r\n    }\r\n  } \r\n}\r\nnav.guilds_c48ade {\r\n  margin-bottom: 0 !important;\r\n}\r\n.sidebar_c48ade:after {\r\n  display: none;\r\n}\r\n/* BetterFolders fix (delete if you don't use) */\r\n .vc-betterFolders-sidebar~section.panels_c48ade {\r\n  left: calc(var(--custom-guild-list-width)*2  + var(--space-xs));\r\n  width: calc(100% - var(--custom-guild-list-width)*2 - var(--space-xs)*2 ) !important;\r\n} \r\n\r\n.typingDots_b88801 > .ellipsis_b88801+.text_b88801 {\r\n  font-size: 0;\r\n  height: 16px;\r\n  >strong {\r\n    font-size: 12px;\r\n    &::after {\r\n      color: var(--text-secondary);\r\n      font-weight: 500;\r\n    }\r\n    &:last-child::after {\r\n      content: \" is yapping shit...\";\r\n    }\r\n    &:last-child:not(:first-child)::after {\r\n      content: \" are yapping shit...\";\r\n    }\r\n    &:nth-last-child(2)::after {\r\n      content: \" and \"\r\n    }\r\n    &:nth-last-child(3)::after {\r\n      content: \", \";\r\n    }\r\n  }\r\n  &:not(:has(>strong))::after {\r\n    font-size: 12px;\r\n    content: \"Several people are yapping shit...\";\r\n  }\r\n}\r\n\r\n/* Remove Profile Reactions */\r\n[class*='statusPopover'], [class*='avatarPopover__'], [class*='activityPopover__'] {display:none;}\r\n\r\n#app-mount\r\n{\r\n  .wrapper__44b0c\r\n  {\r\n    rect\r\n    {\r\n      &[fill='#23a55a'],\r\n      &[fill='#43a25a']\r\n      {\r\n        stroke: var(--rs-online-color);\r\n      }\r\n      &[fill='#f0b232'],\r\n      &[fill='#ca9654']\r\n      {\r\n        stroke: var(--rs-idle-color);\r\n      }\r\n      &[fill='#f23f43'],\r\n      &[fill='#d83a42']\r\n      {\r\n        stroke: var(--rs-dnd-color);\r\n      }\r\n    }\r\n  }\r\n}\r\n\r\n.scroller_fcb628 .section_bf424d {\r\n  &:nth-last-of-type(2) {\r\n    margin-bottom: unset !important;\r\n  }\r\n\r\n  &:nth-last-of-type(1) {\r\n    display: unset !important;\r\n    margin-bottom: 50px;\r\n  }\r\n}"
}